xpy_teal/__init__.py
xpy_teal/Codes/__init__.py
xpy_teal/Codes/config.py
xpy_teal/Codes/dataIO.py
xpy_teal/Codes/download_xp_spectra.py
xpy_teal/Codes/line_analysis.py
xpy_teal/Codes/math_tools.py
xpy_teal/Codes/spectrum_tools.py
xpy_teal/Codes/xpy_teal_pipeline.py
xpy_teal/Configuration_Data/BasisTransformationMatrix_BP.csv
xpy_teal/Configuration_Data/BasisTransformationMatrix_RP.csv
xpy_teal/Configuration_Data/DerivativeMatrix_D1.csv
xpy_teal/Configuration_Data/DerivativeMatrix_D2.csv
xpy_teal/Configuration_Data/DerivativeMatrix_D3.csv
xpy_teal/Configuration_Data/DerivativeMatrix_D4.csv
xpy_teal/Configuration_Data/HermiteIntegrals.csv
xpy_teal/Configuration_Data/LSFModel_BP.csv
xpy_teal/Configuration_Data/LSFModel_RP.csv
xpy_teal/Configuration_Data/RootMatrix_H.csv
xpy_teal/Configuration_Data/bpC03_v375wi_dispersion.csv
xpy_teal/Configuration_Data/bpC03_v375wi_response.csv
xpy_teal/Configuration_Data/rpC03_v142r_dispersion.csv
xpy_teal/Configuration_Data/rpC03_v142r_response.csv
xpy_teal-1.1.0.dist-info/METADATA
xpy_teal-1.1.0.dist-info/WHEEL
xpy_teal-1.1.0.dist-info/licenses/LICENSE
xpy_teal-1.1.0.dist-info/RECORD
