Metadata-Version: 2.4
Name: xpy-teal
Version: 1.1.0
Summary: XPy-Teal: XP Tool for Emission and Absorption Lines
Project-URL: Homepage, https://github.com/malhotrasagar15/xpy_teal
Project-URL: Bug Tracker, https://github.com/malhotrasagar15/xpy_teal/issues
Project-URL: Source, https://github.com/malhotrasagar15/xpy_teal
Author-email: Sagar Malhotra <malhotrasagar15@gmail.com>, Michael Weiler <mweiler@fqa.ub.edu>
License:                     GNU GENERAL PUBLIC LICENSE
License-File: LICENSE
Requires-Python: >=3.10
Requires-Dist: astroquery>=0.4.11
Requires-Dist: ipykernel>=7.1.0
Requires-Dist: joblib>=1.5.2
Requires-Dist: numpy>=2.2.6
Requires-Dist: pandas>=2.3.3
Requires-Dist: scipy>=1.15.3
